scico/__init__.py
scico/_autograd.py
scico/_version.py
scico/denoiser.py
scico/diagnostics.py
scico/examples.py
scico/function.py
scico/loss.py
scico/metric.py
scico/plot.py
scico/random.py
scico/solver.py
scico/typing.py
scico/util.py
scico/data/__init__.py
scico/data/examples/kodim23.png
scico/data/flax/README.rst
scico/data/flax/dncnn17H.mpk
scico/data/flax/dncnn17L.mpk
scico/data/flax/dncnn17M.mpk
scico/data/flax/dncnn17N.mpk
scico/data/flax/dncnn6H.mpk
scico/data/flax/dncnn6L.mpk
scico/data/flax/dncnn6M.mpk
scico/data/flax/dncnn6N.mpk
scico/flax/__init__.py
scico/flax/_flax.py
scico/flax/_models.py
scico/flax/blocks.py
scico/flax/inverse.py
scico/flax/examples/__init__.py
scico/flax/examples/data_generation.py
scico/flax/examples/data_preprocessing.py
scico/flax/examples/examples.py
scico/flax/examples/typed_dict.py
scico/flax/train/__init__.py
scico/flax/train/apply.py
scico/flax/train/checkpoints.py
scico/flax/train/clu_utils.py
scico/flax/train/diagnostics.py
scico/flax/train/input_pipeline.py
scico/flax/train/learning_rate.py
scico/flax/train/losses.py
scico/flax/train/spectral.py
scico/flax/train/state.py
scico/flax/train/steps.py
scico/flax/train/trainer.py
scico/flax/train/traversals.py
scico/flax/train/typed_dict.py
scico/functional/__init__.py
scico/functional/_denoiser.py
scico/functional/_dist.py
scico/functional/_functional.py
scico/functional/_indicator.py
scico/functional/_norm.py
scico/functional/_proxavg.py
scico/functional/_tvnorm.py
scico/linop/__init__.py
scico/linop/_circconv.py
scico/linop/_convolve.py
scico/linop/_dft.py
scico/linop/_diag.py
scico/linop/_diff.py
scico/linop/_func.py
scico/linop/_grad.py
scico/linop/_linop.py
scico/linop/_matrix.py
scico/linop/_stack.py
scico/linop/_util.py
scico/linop/abel.py
scico/linop/optics.py
scico/linop/xray/__init__.py
scico/linop/xray/_xray.py
scico/linop/xray/astra.py
scico/linop/xray/svmbir.py
scico/numpy/__init__.py
scico/numpy/_blockarray.py
scico/numpy/_wrapped_function_lists.py
scico-0.0.6.dist-info/LICENSE
scico-0.0.6.dist-info/METADATA
scico-0.0.6.dist-info/WHEEL
scico-0.0.6.dist-info/top_level.txt
scico-0.0.6.dist-info/RECORD
